ScoreDraft/SimpleInstruments.py
ScoreDraft/PyMeteorGenerator.cpython-35m-x86_64-linux-gnu.so
ScoreDraft/PercussionSampler.py
ScoreDraft/VCCVLyricSet.data
ScoreDraft/Singer.py
ScoreDraft/TTEnglishConverter.py
ScoreDraft/Instrument.py
ScoreDraft/Document.py
ScoreDraft/RapChinese.py
ScoreDraft/Meteor.py
ScoreDraft/TTLyricSet.data
ScoreDraft/CVVCChineseConverter.py
ScoreDraft/TsuroVCVConverter.py
ScoreDraft/XiaYYConverter.py
ScoreDraft/Catalog.py
ScoreDraft/VCCVEnglishConverter.py
ScoreDraft/Percussion.py
ScoreDraft/__init__.py
ScoreDraft/JPVCVConverter.py
ScoreDraft/SF2Instrument.py
ScoreDraft/UtauDraft.py
ScoreDraft/Notes.py
ScoreDraft/InstrumentSampler.py
SingingGadgets-0.0.3.dist-info/top_level.txt
SingingGadgets-0.0.3.dist-info/WHEEL
SingingGadgets-0.0.3.dist-info/RECORD
SingingGadgets-0.0.3.dist-info/METADATA
SingingGadgets/SimpleInstruments.py
SingingGadgets/SF2Synth.py
SingingGadgets/PyBasicSamplers.cpython-35m-x86_64-linux-gnu.so
SingingGadgets/SF2.py
SingingGadgets/PyVoiceSampler.cpython-35m-x86_64-linux-gnu.so
SingingGadgets/BasicSamplers.py
SingingGadgets/PySF2Synth.cpython-35m-x86_64-linux-gnu.so
SingingGadgets/PySimpleInstruments.cpython-35m-x86_64-linux-gnu.so
SingingGadgets/VoiceSampler.py
SingingGadgets/PyTrackBuffer.cpython-35m-x86_64-linux-gnu.so
SingingGadgets/__init__.py
SingingGadgets/TrackBuffer.py
SingingGadgets/PyWavUtils.cpython-35m-x86_64-linux-gnu.so
SingingGadgets/SF2Presets.py
SingingGadgets/UTAUUtils.py
